.coveragerc
.editorconfig
.gitignore
.travis.yml
LICENSE
README.md
pyproject.toml
requirements.txt
requirements_dev.txt
setup.cfg
setup.py
.github/workflows/python-publish.yml
democritus_archives/__init__.py
democritus_archives/archive.py
democritus_archives/archive_temp_utils.py
democritus_archives.egg-info/PKG-INFO
democritus_archives.egg-info/SOURCES.txt
democritus_archives.egg-info/dependency_links.txt
democritus_archives.egg-info/requires.txt
democritus_archives.egg-info/top_level.txt
democritus_archives.egg-info/zip-safe
tests/__init__.py
tests/test_archive.py
tests/test_archive_utils.py